DTT/__init__.py
DTT/deepLTranslate.py
DeeptransTool-1.4.dist-info/LICENSE
DeeptransTool-1.4.dist-info/METADATA
DeeptransTool-1.4.dist-info/WHEEL
DeeptransTool-1.4.dist-info/top_level.txt
DeeptransTool-1.4.dist-info/RECORD
