Metadata-Version: 2.1
Name: DeeptransTool
Version: 1.4
Summary: Use the world's best translator (DeepL) to translate your text files or text itself!! All without having to provide your credit card or be limited by the API. 🐸
Home-page: https://github.com/ElHaban3ro/DeeptransTool
Author: ElHaban3ro
Author-email: habanferd@gmail.com
License: GPLv3
Keywords: Translate,DeepL,Traduccion,API,Translation
Classifier: Programming Language :: Python :: 3.11
License-File: LICENSE
Requires-Dist: selenium (==4.5.0)
Requires-Dist: webdriver-manager (==3.8.3)
Requires-Dist: PyPDF2
Requires-Dist: beautifulsoup4
